lihu46382_mcp_demo/__init__.py
lihu46382_mcp_demo-0.1.0.dist-info/WHEEL
lihu46382_mcp_demo-0.1.0.dist-info/entry_points.txt
lihu46382_mcp_demo-0.1.0.dist-info/METADATA
lihu46382_mcp_demo-0.1.0.dist-info/RECORD
